{
  "generated_at": "2026-05-11T22:08:03.027300+07:00",
  "items": [
    {
      "ticker": "GOTO.JK",
      "current_price_native": 50.0,
      "current_price_idr": 50.0,
      "native_currency": "IDR",
      "daily_change_pct": 0.0,
      "previous_close": 50.0
    },
    {
      "ticker": "AMMN.JK",
      "current_price_native": 4130.0,
      "current_price_idr": 4130.0,
      "native_currency": "IDR",
      "daily_change_pct": -1.9,
      "previous_close": 4210.0
    },
    {
      "ticker": "BBCA.JK",
      "current_price_native": 6150.0,
      "current_price_idr": 6150.0,
      "native_currency": "IDR",
      "daily_change_pct": -0.4,
      "previous_close": 6175.0
    },
    {
      "ticker": "TSLA",
      "current_price_native": 426.045,
      "current_price_idr": 7417443.68,
      "native_currency": "USD",
      "daily_change_pct": -0.54,
      "previous_close": 428.3500061035156
    },
    {
      "ticker": "NVDA",
      "current_price_native": 221.535,
      "current_price_idr": 3856924.41,
      "native_currency": "USD",
      "daily_change_pct": 2.94,
      "previous_close": 215.1999969482422
    },
    {
      "ticker": "BTC-USD",
      "current_price_native": 80876.8203,
      "current_price_idr": 1408065441.64,
      "native_currency": "USD",
      "daily_change_pct": -1.54,
      "previous_close": 82138.9296875
    },
    {
      "ticker": "ETH-USD",
      "current_price_native": 2315.5701,
      "current_price_idr": 40314074.89,
      "native_currency": "USD",
      "daily_change_pct": -2.26,
      "previous_close": 2369.0439453125
    },
    {
      "ticker": "INET.JK",
      "current_price_native": 288.0,
      "current_price_idr": 288.0,
      "native_currency": "IDR",
      "daily_change_pct": -3.36,
      "previous_close": 298.0
    }
  ]
}