{
  "generated_at": "2026-05-13T19:07:28.269965+07:00",
  "items": [
    {
      "ticker": "GOTO.JK",
      "current_price_native": 50.0,
      "current_price_idr": 50.0,
      "native_currency": "IDR",
      "daily_change_pct": 0.0,
      "previous_close": 50.0
    },
    {
      "ticker": "AMMN.JK",
      "current_price_native": 3700.0,
      "current_price_idr": 3700.0,
      "native_currency": "IDR",
      "daily_change_pct": -9.09,
      "previous_close": 4070.0
    },
    {
      "ticker": "BBCA.JK",
      "current_price_native": 6100.0,
      "current_price_idr": 6100.0,
      "native_currency": "IDR",
      "daily_change_pct": -0.41,
      "previous_close": 6125.0
    },
    {
      "ticker": "TSLA",
      "current_price_native": 433.45,
      "current_price_idr": 7568037.21,
      "native_currency": "USD",
      "daily_change_pct": -2.6,
      "previous_close": 445.0
    },
    {
      "ticker": "NVDA",
      "current_price_native": 220.78,
      "current_price_idr": 3854818.78,
      "native_currency": "USD",
      "daily_change_pct": 0.61,
      "previous_close": 219.44000244140625
    },
    {
      "ticker": "BTC-USD",
      "current_price_native": 80495.6562,
      "current_price_idr": 1405454158.12,
      "native_currency": "USD",
      "daily_change_pct": 0.02,
      "previous_close": 80477.4921875
    },
    {
      "ticker": "ETH-USD",
      "current_price_native": 2304.1899,
      "current_price_idr": 40231156.38,
      "native_currency": "USD",
      "daily_change_pct": 1.3,
      "previous_close": 2274.6435546875
    },
    {
      "ticker": "INET.JK",
      "current_price_native": 284.0,
      "current_price_idr": 284.0,
      "native_currency": "IDR",
      "daily_change_pct": 0.71,
      "previous_close": 282.0
    }
  ]
}