{
  "generated_at": "2026-05-07T04:17:29.903893+07:00",
  "items": [
    {
      "ticker": "GOTO.JK",
      "current_price_native": 50.0,
      "current_price_idr": 50.0,
      "native_currency": "IDR",
      "daily_change_pct": 0.0,
      "previous_close": 50.0
    },
    {
      "ticker": "AMMN.JK",
      "current_price_native": 5000.0,
      "current_price_idr": 5000.0,
      "native_currency": "IDR",
      "daily_change_pct": -3.38,
      "previous_close": 5175.0
    },
    {
      "ticker": "BBCA.JK",
      "current_price_native": 5950.0,
      "current_price_idr": 5950.0,
      "native_currency": "IDR",
      "daily_change_pct": 0.0,
      "previous_close": 5950.0
    },
    {
      "ticker": "TSLA",
      "current_price_native": 398.73,
      "current_price_idr": 6937902.19,
      "native_currency": "USD",
      "daily_change_pct": 2.4,
      "previous_close": 389.3699951171875
    },
    {
      "ticker": "NVDA",
      "current_price_native": 207.83,
      "current_price_idr": 3616242.03,
      "native_currency": "USD",
      "daily_change_pct": 5.77,
      "previous_close": 196.5
    },
    {
      "ticker": "BTC-USD",
      "current_price_native": 80927.0547,
      "current_price_idr": 1408130751.56,
      "native_currency": "USD",
      "daily_change_pct": 1.38,
      "previous_close": 79827.90625
    },
    {
      "ticker": "ETH-USD",
      "current_price_native": 2361.1826,
      "current_price_idr": 41084577.54,
      "native_currency": "USD",
      "daily_change_pct": 0.63,
      "previous_close": 2346.39697265625
    },
    {
      "ticker": "INET.JK",
      "current_price_native": 312.0,
      "current_price_idr": 312.0,
      "native_currency": "IDR",
      "daily_change_pct": -1.27,
      "previous_close": 316.0
    }
  ]
}